spritemaker.py
spritemaker-1.0.0.dist-info/METADATA
spritemaker-1.0.0.dist-info/WHEEL
spritemaker-1.0.0.dist-info/top_level.txt
spritemaker-1.0.0.dist-info/RECORD
